python_find/__init__.py
python_find/__main__.py
python_find/find.py
python_find/tree_search.py
python_find-0.1.dist-info/DESCRIPTION.rst
python_find-0.1.dist-info/METADATA
python_find-0.1.dist-info/RECORD
python_find-0.1.dist-info/WHEEL
python_find-0.1.dist-info/metadata.json
python_find-0.1.dist-info/top_level.txt
