Metadata-Version: 2.0
Name: python-find
Version: 0.1
Summary: UNKNOWN
Home-page: UNKNOWN
Author: Andrew Bryant
Author-email: abryant288@gmail.com
License: MIT
Platform: UNKNOWN
